pyintegrity/API579.py
pyintegrity/__init__.py
pyintegrity/__main__.py
pyintegrity/common/API579_components.py
pyintegrity/common/ApplicationManager.py
pyintegrity/common/DataFrame_To_Image.py
pyintegrity/common/DataFrame_To_doc.py
pyintegrity/common/DataFrame_To_xlsx.py
pyintegrity/common/__init__.py
pyintegrity/common/data.py
pyintegrity/common/database.py
pyintegrity/common/pipe_components.py
pyintegrity/common/set_logging.py
pyintegrity/common/update_deep.py
pyintegrity/common/ymlInput.py
pyintegrity/custom/MaterialProperties.py
pyintegrity/custom/PipeCapacity.py
pyintegrity/custom/PipeSizing.py
pyintegrity/custom/API579/__init__.py
pyintegrity/custom/API579/customInputs.py
pyintegrity/custom/API579/plotContour.py
pyintegrity/custom/API579/plotContourf.py
pyintegrity/custom/API579/plotCustom.py
pyintegrity/custom/API579/plotDefault.py
pyintegrity/custom/API579/plotHeatMap.py
pyintegrity/custom/API579/saveData.py
pyintegrity/custom/API579/testcontour.py
pyintegrity/custom/ASMEB31/__init__.py
pyintegrity/custom/ASMEB31/plotCustom.py
pyintegrity/custom/ASMEB31/plotDefault.py
pyintegrity/custom/ASMEB31/saveData.py
pyintegrity/tests/__init__.py
pyintegrity/tests/test_pyintegrity_gml_lml_api1111_1.py
pyintegrity/tests/test_pyintegrity_gml_lml_b314_1.py
pyintegrity/tests/test_pyintegrity_gml_lml_b314_2.py
pyintegrity/tests/test_pyintegrity_gml_lml_b318_1.py
pyintegrity-0.0.1.dist-info/METADATA
pyintegrity-0.0.1.dist-info/WHEEL
pyintegrity-0.0.1.dist-info/entry_points.txt
pyintegrity-0.0.1.dist-info/top_level.txt
pyintegrity-0.0.1.dist-info/RECORD
