Metadata-Version: 2.1
Name: pyintegrity
Version: 0.0.1
Summary: fitness for service for metallic pipes
Author-email: Vamsee Achanta <vamsee.achanta@aceengineer.com>
Project-URL: repository, https://github.com/vamseeachanta/pyintegrity
Project-URL: documentation, https://github.com/vamseeachanta/pyintegrity/blob/main/README.md
Keywords: fitness for service,condition based monitoring,CBM,api579,api510,asme b31g,bs7910,api rp 2rd
Classifier: License :: OSI Approved :: MIT License
Classifier: Programming Language :: Python
Classifier: Programming Language :: Python :: 3
Requires-Python: >=3.7
Requires-Dist: pyyaml
Requires-Dist: openpyxl
Requires-Dist: pandas
Requires-Dist: numpy
Requires-Dist: matplotlib
Requires-Dist: plotly
Requires-Dist: tomli ; python_version < "3.11"
Provides-Extra: build
Requires-Dist: build ; extra == 'build'
Requires-Dist: twine ; extra == 'build'
Provides-Extra: dev
Requires-Dist: black ; extra == 'dev'
Requires-Dist: bumpver ; extra == 'dev'
Requires-Dist: isort ; extra == 'dev'
Requires-Dist: mypy ; extra == 'dev'
Requires-Dist: pytest ; extra == 'dev'
